README.md
setup.py
FW/__init__.py
FW/Core/Extractor.py
FW/Core/HttpRequest.py
FW/Core/Soup.py
FW/Core/Tag.py
FW/Core/UrlTester.py
FW/Core/Validator.py
FW/Core/__init__.py
FW/Core/CoreDownloaders/ArchiveDownloader_v1.py
FW/Core/CoreDownloaders/ArticleDownloader.py
FW/Core/CoreDownloaders/MediaDownloaders.py
FW/Core/CoreDownloaders/UI.py
FW/Core/CoreDownloaders/__init__.py
FW/Crawler/Crawl.py
FW/Crawler/UrlExtractor.py
FW/Crawler/UrlProcess.py
FW/Crawler/UrlQueue.py
FW/Crawler/__init__.py
FW/FairSocket/Client.py
FW/FairSocket/DuckDNS.py
FW/FairSocket/FusedSocket.py
FW/FairSocket/Message.py
FW/FairSocket/Server.py
FW/FairSocket/__init__.py
FW/FusedDownloader/FusedDownloader.py
FW/FusedDownloader/__init__.py
FW/JParser/JsonParser.py
FW/JParser/Keys.py
FW/JParser/__init__.py
FairWEB.egg-info/PKG-INFO
FairWEB.egg-info/SOURCES.txt
FairWEB.egg-info/dependency_links.txt
FairWEB.egg-info/requires.txt
FairWEB.egg-info/top_level.txt