Metadata-Version: 2.1
Name: FairWEB
Version: 4.5.0
Summary: Full HTML WebPage Downloader, Parser and Data Extractor. Web Crawler, Server and Client Included.
Home-page: https://github.com/chazzcoin/fairweb
Author: ChazzCoin
Author-email: chazzcoin@gmail.com
License: BSD 2-clause
Platform: UNKNOWN
Classifier: Development Status :: 1 - Planning
Classifier: Intended Audience :: Science/Research
Classifier: License :: OSI Approved :: BSD License
Classifier: Operating System :: POSIX :: Linux
Classifier: Programming Language :: Python :: 3.8
Classifier: Programming Language :: Python :: 3.9
